[{"y":2011,"min":[null,null,null,null,null,null,null,null,null,null,null,null,null,null,null,null,null,null,null,null,null,null,null,null,null,null,null,null,null,null,null,null,null,null,null,null,null,null,null,null,null,null,null,null,null,null,null,null,null,null,null,null,null,null,null,null,null,null,null,null,null,null,null,null,null,null,null,null,null,null,null,null,null,null,null,null,null,null,null,null,null,null,null,null,null,null,null,null,null,null,null,null,null,null,null,null,null,null,null,null,null,null,null,null,null,null,null,null,null,null,null,null,null,null,null,null,null,null,null,null,null,null,null,null,null,null,null,null,null,null,null,null,null,null,null,null,null,null,null,null,null,null,null,null,null,null,null,null,null,null,null,null,null,null,null,null,null,null,null,null,null,null,null,null,null,null,null,null,null,null,null,null,null,null,null,null,null,null,null,null,null,null,null,null,null,null,null,null,null,null,null,null,null,null,null,null,null,null,null,null,null,null,null,null,null,null,null,null,null,null,null,null,null,null,null,null,null,null,null,null,null,null,null,null,null,null,null,null,null,null,null,null,null,null,null,null,null,null,null,null,null,null,null,null,null,null,null,null,null,50.3,50.32,50.28,50.25,50.24,50.29,50.33,null,null,null,null,null,null,null,null,null,null,null,null,null,null,null,null,null,null,null,null,null,null,null,null,null,null,null,null,null,null,null,null,null,null,null,null,null,null,null,null,null,null,null,null,null,null,null,null,null,null,null,50.27,50.24,50.28,50.25,50.25,50.26,null,50.21,50.27,50.25,50.27,50.23,50.25,50.28,50.27,50.24,50.23,50.27,50.27,50.27,50.29,50.27,50.31,50.36,50.26,50.27,50.27,50.25,50.27,50.28,50.31,50.29,50.3,50.29,50.29,50.3,50.29,50.27,50.25,null,null,null,null,null,null,null,null,null,null,null,null,null,null,null,null,null,null,null],"max":[null,null,null,null,null,null,null,null,null,null,null,null,null,null,null,null,null,null,null,null,null,null,null,null,null,null,null,null,null,null,null,null,null,null,null,null,null,null,null,null,null,null,null,null,null,null,null,null,null,null,null,null,null,null,null,null,null,null,null,null,null,null,null,null,null,null,null,null,null,null,null,null,null,null,null,null,null,null,null,null,null,null,null,null,null,null,null,null,null,null,null,null,null,null,null,null,null,null,null,null,null,null,null,null,null,null,null,null,null,null,null,null,null,null,null,null,null,null,null,null,null,null,null,null,null,null,null,null,null,null,null,null,null,null,null,null,null,null,null,null,null,null,null,null,null,null,null,null,null,null,null,null,null,null,null,null,null,null,null,null,null,null,null,null,null,null,null,null,null,null,null,null,null,null,null,null,null,null,null,null,null,null,null,null,null,null,null,null,null,null,null,null,null,null,null,null,null,null,null,null,null,null,null,null,null,null,null,null,null,null,null,null,null,null,null,null,null,null,null,null,null,null,null,null,null,null,null,null,null,null,null,null,null,null,null,null,null,null,null,null,null,null,null,null,null,null,null,null,null,50.43,50.41,50.41,50.38,50.36,50.41,50.41,null,null,null,null,null,null,null,null,null,null,null,null,null,null,null,null,null,null,null,null,null,null,null,null,null,null,null,null,null,null,null,null,null,null,null,null,null,null,null,null,null,null,null,null,null,null,null,null,null,null,null,50.36,50.36,50.37,50.35,50.34,50.34,null,50.28,50.39,50.35,50.35,50.33,50.34,50.36,50.37,50.37,50.35,50.36,50.35,50.35,50.38,50.37,50.43,50.45,50.4,50.37,50.4,50.35,50.38,50.4,50.42,50.43,50.4,50.47,50.45,50.44,50.4,50.35,50.26,null,null,null,null,null,null,null,null,null,null,null,null,null,null,null,null,null,null,null]},{"y":2012,"min":[null,null,null,null,null,null,null,null,null,null,null,null,null,null,null,50.32,50.3,50.29,50.33,50.31,50.31,50.38,50.34,50.33,50.3,50.27,50.29,50.27,50.28,50.23,50.22,50.26,null,null,null,null,50.28,50.31,50.31,50.31,50.3,50.31,null,50.3,50.31,50.33,50.3,50.3,50.29,50.31,50.31,50.32,50.3,50.36,50.36,50.31,50.3,50.29,50.33,50.29,50.29,50.29,50.31,50.3,50.26,50.27,50.28,null,null,null,null,null,null,null,null,null,null,null,50.31,50.3,50.28,50.25,50.26,50.28,50.28,50.28,50.27,50.3,50.31,50.3,50.32,50.3,50.3,50.25,50.24,50.26,50.28,50.27,50.26,50.26,50.26,50.27,50.27,50.26,50.28,50.29,50.28,50.27,50.26,50.25,50.25,50.25,50.26,50.26,50.26,50.25,50.26,50.28,50.24,50.23,50.24,50.26,50.25,50.26,50.25,50.3,50.24,50.26,50.24,50.26,50.27,50.32,50.31,50.28,50.27,50.26,50.3,50.24,50.23,50.26,50.28,50.25,50.21,50.26,50.2,50.23,50.26,50.29,50.26,50.28,50.27,50.23,50.3,50.29,50.28,50.27,50.29,50.25,50.28,50.27,50.28,50.29,50.26,50.25,50.26,50.22,50.25,50.26,50.27,50.24,50.26,50.25,50.27,null,null,null,null,50.3,50.27,50.26,50.26,50.28,null,50.26,50.24,50.26,50.25,50.27,50.27,50.28,50.28,50.29,50.28,50.28,50.28,50.29,50.3,50.31,50.31,50.3,50.3,50.29,50.27,50.28,50.27,50.24,50.26,50.26,50.24,50.28,50.28,50.27,50.27,50.22,50.26,50.27,50.29,50.27,50.29,50.28,50.27,50.27,50.26,50.27,50.23,50.23,50.24,50.22,50.26,50.26,50.26,50.28,50.3,50.31,50.32,50.28,50.26,50.29,50.29,50.28,50.25,50.25,50.26,50.25,50.27,50.28,50.27,50.27,50.28,50.28,50.28,50.27,50.26,50.28,50.29,50.29,50.28,50.3,50.29,50.28,50.28,50.29,50.27,50.27,50.22,50.26,50.23,50.23,50.27,50.27,null,null,null,50.29,50.28,50.28,50.29,50.3,50.28,50.28,50.29,50.29,50.32,50.3,50.25,50.25,50.26,50.28,50.27,50.27,50.27,50.29,50.26,50.28,50.27,50.23,50.23,50.25,50.28,50.23,50.28,50.29,50.29,50.3,50.24,50.27,50.28,50.28,50.28,50.32,50.3,50.32,50.3,50.24,50.26,50.3,50.29,50.27,50.26,50.26,50.25,50.28,50.3,50.26,50.25,50.26,50.26,50.24,50.25,50.25,50.27,50.28,50.29,50.31,50.28,50.27,50.28,50.28,50.28,50.27,50.26,50.21,50.25,50.29,50.31,50.3,50.27,50.25,50.25,50.27,null,50.29,50.31,50.26,50.23,50.22,50.25,50.27,50.29,50.28,50.33,50.29,50.27,50.27,50.3,50.29],"max":[null,null,null,null,null,null,null,null,null,null,null,null,null,null,null,50.39,50.41,50.38,50.43,50.47,50.44,50.49,50.48,50.41,50.4,50.36,50.37,50.35,50.38,50.33,50.32,50.26,null,null,null,null,50.35,50.34,50.44,50.33,50.31,50.31,null,50.32,50.35,50.35,50.33,50.36,50.31,50.42,50.38,50.42,50.4,50.46,50.45,50.4,50.4,50.4,50.41,50.4,50.36,50.37,50.31,50.38,50.38,50.37,50.28,null,null,null,null,null,null,null,null,null,null,null,50.4,50.43,50.36,50.35,50.36,50.28,50.38,50.37,50.38,50.39,50.42,50.41,50.47,50.41,50.41,50.39,50.35,50.34,50.37,50.37,50.37,50.38,50.35,50.39,50.37,50.37,50.28,50.39,50.38,50.37,50.36,50.37,50.34,50.35,50.39,50.36,50.35,50.4,50.37,50.37,50.35,50.36,50.36,50.36,50.37,50.36,50.38,50.3,50.37,50.37,50.34,50.36,50.37,50.41,50.4,50.36,50.36,50.36,50.3,50.35,50.3,50.37,50.37,50.42,50.33,50.35,50.34,50.35,50.35,50.4,50.35,50.39,50.38,50.36,50.39,50.38,50.36,50.38,50.4,50.34,50.34,50.38,50.39,50.37,50.37,50.37,50.37,50.33,50.33,50.34,50.4,50.41,50.34,50.33,50.27,null,null,null,null,50.4,50.37,50.36,50.36,50.38,null,50.34,50.35,50.35,50.35,50.37,50.37,50.37,50.42,50.4,50.37,50.4,50.38,50.4,50.39,50.42,50.43,50.42,50.43,50.38,50.35,50.3,50.36,50.34,50.36,50.37,50.36,50.39,50.41,50.37,50.38,50.31,50.38,50.35,50.39,50.34,50.41,50.38,50.38,50.34,50.39,50.38,50.33,50.4,50.34,50.33,50.38,50.35,50.34,50.37,50.41,50.38,50.41,50.39,50.35,50.36,50.4,50.38,50.32,50.34,50.34,50.37,50.39,50.38,50.35,50.36,50.37,50.38,50.39,50.36,50.36,50.37,50.39,50.38,50.38,50.4,50.41,50.38,50.39,50.37,50.38,50.36,50.34,50.4,50.35,50.35,50.35,50.36,null,null,null,50.39,50.35,50.36,50.37,50.41,50.4,50.4,50.41,50.37,50.37,50.37,50.36,50.36,50.39,50.36,50.38,50.36,50.36,50.36,50.35,50.36,50.37,50.32,50.34,50.37,50.37,50.38,50.38,50.38,50.36,50.39,50.35,50.36,50.36,50.38,50.38,50.42,50.39,50.41,50.41,50.35,50.34,50.38,50.39,50.39,50.35,50.35,50.35,50.35,50.36,50.34,50.34,50.34,50.4,50.33,50.33,50.41,50.35,50.36,50.37,50.38,50.37,50.37,50.36,50.35,50.41,50.37,50.41,50.3,50.35,50.39,50.41,50.38,50.35,50.33,50.33,50.34,null,50.37,50.4,50.35,50.33,50.31,50.34,50.37,50.37,50.36,50.36,50.39,50.34,50.35,50.41,50.42]},{"y":2013,"min":[50.28,50.32,50.29,50.3,50.33,50.32,50.3,50.3,50.31,50.27,50.32,50.31,50.27,50.28,50.26,50.28,50.28,50.25,50.22,50.21,50.2,50.24,50.27,50.25,50.24,50.25,50.25,50.29,50.26,50.29,50.33,50.27,50.32,50.32,50.28,50.31,50.29,50.28,50.29,50.31,50.28,50.23,50.23,50.27,50.22,50.26,50.27,50.24,50.28,50.3,50.29,50.29,50.27,50.26,50.28,50.27,50.28,50.26,50.28,50.28,50.29,50.3,50.28,50.28,50.28,50.22,50.2,50.21,50.26,50.27,50.27,50.29,50.26,50.22,50.25,null,50.24,50.25,50.23,50.3,50.23,50.12,50.09,50.09,50.17,50.22,50.25,50.26,50.3,50.3,50.3,50.26,50.24,50.22,50.24,50.25,null,null,50.23,50.25,50.25,50.28,50.31,50.29,50.3,50.3,50.28,50.28,50.3,50.28,50.26,50.27,50.27,50.27,50.26,50.3,null,null,50.3,50.29,50.26,50.24,50.26,50.28,50.28,50.21,50.26,50.26,50.28,50.29,50.29,50.28,50.28,50.25,50.22,50.22,50.3,50.32,50.28,50.31,50.31,50.33,50.32,50.29,50.31,50.36,50.35,50.26,50.27,50.29,50.29,50.32,50.33,50.3,50.3,50.27,50.27,50.28,50.29,50.28,50.3,50.28,50.29,50.24,50.28,50.25,50.28,50.24,50.27,50.25,50.27,50.27,50.28,50.3,null,50.3,50.29,50.29,50.26,50.28,50.3,50.3,50.31,50.29,50.31,50.27,50.24,50.27,50.27,50.28,50.29,50.3,50.27,50.28,50.28,50.25,50.29,50.32,50.3,50.31,50.3,50.28,50.29,50.27,50.28,null,null,null,null,50.31,50.33,50.32,50.26,50.27,50.28,50.3,50.26,50.29,50.23,50.28,50.27,50.3,50.33,50.33,50.34,50.31,50.29,50.3,50.28,null,50.33,50.32,50.29,50.27,50.23,50.19,50.22,50.26,50.28,50.25,null,50.32,50.29,50.32,50.34,50.31,50.27,50.26,50.25,50.28,50.31,50.3,50.26,50.28,50.29,50.31,50.28,50.32,50.28,50.3,50.29,50.3,50.27,50.3,50.31,50.33,50.31,50.26,50.3,50.29,50.27,50.22,50.24,50.21,50.2,null,null,null,null,null,50.31,50.29,50.3,50.33,50.3,50.28,50.29,50.29,50.29,50.31,50.4,null,null,50.3,50.29,50.3,50.3,50.27,50.28,50.3,50.3,50.33,50.31,50.27,50.31,50.31,50.3,50.3,50.3,50.3,50.31,50.31,50.32,50.31,50.34,50.3,50.3,50.28,50.27,50.28,50.27,50.24,50.29,50.29,50.29,50.31,50.32,50.32,50.31,null,null,null,null,null,null,null,null,null,50.32,50.36,50.43,null,50.34,50.32,50.3,50.28,50.29,50.27,50.28,50.28,50.27,50.26,50.28,50.29,50.3,50.29,50.31,50.32,50.33,50.32,50.29,50.31,50.32,50.3,50.28],"max":[50.34,50.42,50.4,50.41,50.4,50.34,50.37,50.4,50.4,50.39,50.4,50.4,50.35,50.38,50.38,50.34,50.38,50.35,50.3,50.3,50.31,50.34,50.39,50.37,50.33,50.34,50.37,50.39,50.4,50.43,50.45,50.41,50.42,50.43,50.45,50.45,50.43,50.42,50.39,50.4,50.39,50.31,50.4,50.38,50.34,50.36,50.37,50.34,50.37,50.42,50.37,50.4,50.38,50.35,50.34,50.39,50.36,50.33,50.39,50.39,50.41,50.41,50.37,50.38,50.39,50.33,50.29,50.29,50.35,50.37,50.38,50.37,50.38,50.34,50.32,null,50.35,50.38,50.34,50.39,50.34,50.26,50.23,50.22,50.3,50.34,50.34,50.37,50.38,50.38,50.37,50.36,50.34,50.35,50.34,50.32,null,null,50.33,50.35,50.35,50.4,50.45,50.36,50.41,50.42,50.38,50.46,50.4,50.38,50.37,50.38,50.41,50.38,50.38,50.32,null,null,50.43,50.36,50.37,50.36,50.36,50.42,50.35,50.32,50.36,50.37,50.35,50.41,50.41,50.43,50.37,50.39,50.34,50.38,50.4,50.43,50.37,50.32,50.41,50.48,50.38,50.39,50.43,50.45,50.48,50.48,50.39,50.39,50.4,50.43,50.4,50.4,50.43,50.41,50.37,50.37,50.38,50.39,50.43,50.43,50.4,50.37,50.4,50.38,50.42,50.35,50.35,50.37,50.37,50.44,50.38,50.38,null,50.39,50.39,50.37,50.37,50.41,50.37,50.41,50.39,50.41,50.41,50.36,50.33,50.38,50.36,50.35,50.38,50.38,50.37,50.37,50.37,50.36,50.37,50.4,50.4,50.4,50.38,50.39,50.39,50.39,50.38,null,null,null,null,50.4,50.42,50.41,50.36,50.36,50.4,50.4,50.34,50.43,50.38,50.39,50.37,50.39,50.41,50.43,50.43,50.41,50.37,50.38,50.37,null,50.43,50.4,50.4,50.38,50.37,50.34,50.35,50.4,50.42,50.39,null,50.4,50.38,50.41,50.42,50.41,50.36,50.35,50.35,50.41,50.38,50.38,50.38,50.38,50.38,50.39,50.35,50.41,50.4,50.4,50.38,50.41,50.4,50.4,50.32,50.43,50.4,50.38,50.41,50.39,50.4,50.34,50.35,50.37,50.34,null,null,null,null,null,50.4,50.39,50.4,50.42,50.39,50.39,50.39,50.4,50.42,50.48,50.43,null,null,50.4,50.37,50.39,50.41,50.36,50.37,50.41,50.46,50.44,50.4,50.38,50.4,50.41,50.42,50.44,50.39,50.45,50.43,50.4,50.47,50.44,50.45,50.4,50.4,50.38,50.36,50.39,50.36,50.39,50.4,50.4,50.36,50.4,50.4,50.39,50.33,null,null,null,null,null,null,null,null,null,50.49,50.47,50.43,null,50.45,50.43,50.4,50.36,50.37,50.39,50.41,50.38,50.39,50.34,50.38,50.42,50.41,50.4,50.41,50.38,50.38,50.38,50.39,50.4,50.4,50.39,50.37]},{"y":2014,"min":[50.31,50.3,50.27,50.29,50.3,50.29,50.3,50.32,50.3,50.34,50.31,50.3,50.28,50.3,50.3,50.28,50.3,50.29,50.26,50.28,50.3,50.25,50.23,50.26,50.27,null,50.27,50.29,50.22,50.24,50.27,50.26,50.27,50.22,50.26,50.26,50.29,50.28,50.31,50.34,50.28,50.32,50.31,50.29,50.29,50.28,50.37,50.3,50.29,50.3,50.27,50.3,50.3,50.32,50.28,50.28,50.31,50.33,null,null,null,50.27,50.31,50.27,50.28,50.28,50.29,50.3,50.3,50.29,50.29,50.27,50.29,50.35,50.38,50.35,50.32,50.34,50.28,50.29,50.27,50.32,null,null,null,null,null,null,null,null,50.26,50.29,50.27,50.28,50.29,50.3,50.28,50.29,50.33,50.28,50.33,null,null,50.36,50.32,50.26,50.29,50.32,50.27,50.26,50.32,50.32,50.32,50.34,null,null,null,50.27,50.29,50.27,50.29,50.29,50.3,50.3,50.27,50.27,50.29,50.34,null,null,null,null,50.32,50.31,50.26,50.27,50.29,50.28,50.26,50.27,50.28,50.29,50.27,50.27,50.3,50.25,50.28,50.28,50.29,50.32,50.33,50.32,50.32,null,null,null,null,null,null,null,50.29,50.36,50.3,50.31,50.31,50.3,50.31,50.27,50.27,50.29,50.3,50.3,50.31,50.3,50.29,50.29,50.25,50.25,50.28,50.31,50.33,50.3,50.28,50.28,50.28,50.31,50.31,50.29,50.29,50.31,50.31,50.3,50.3,50.31,50.32,50.29,50.29,50.28,50.27,50.27,50.27,50.33,50.3,50.27,50.27,50.28,50.29,50.29,50.3,50.31,50.31,50.34,50.32,50.27,50.31,50.31,50.32,50.29,50.3,50.27,50.29,50.29,50.33,50.28,50.29,50.3,50.28,50.3,50.33,50.31,50.32,50.32,50.3,50.3,50.3,50.3,50.28,50.26,50.27,50.3,null,null,null,null,null,50.29,50.26,50.3,50.32,50.32,50.32,50.33,50.32,50.28,50.29,50.31,50.3,50.3,50.28,50.28,50.3,50.29,50.3,50.32,50.33,50.32,50.33,null,null,null,null,null,null,null,null,null,null,null,null,null,null,null,null,null,null,null,null,null,null,null,null,null,null,null,null,null,null,null,null,null,null,null,null,null,null,null,null,null,null,null,null,null,null,null,null,null,null,null,null,null,null,null,null,null,null,null,null,null,null,null,null,null,null,null,null,null,null,null,null,null,null,null,null,null,null,null,null,null,null,null,null,null,null,null,null,null,null,null,null,null,null,null,null,null,null],"max":[50.34,50.38,50.38,50.39,50.44,50.39,50.38,50.45,50.45,50.46,50.43,50.42,50.38,50.4,50.41,50.38,50.37,50.35,50.34,50.37,50.38,50.35,50.32,50.35,50.27,null,50.42,50.38,50.32,50.32,50.36,50.37,50.38,50.33,50.35,50.37,50.39,50.46,50.39,50.44,50.37,50.43,50.4,50.4,50.4,50.43,50.41,50.41,50.37,50.4,50.36,50.44,50.4,50.41,50.37,50.38,50.38,50.33,null,null,null,50.38,50.42,50.39,50.37,50.38,50.4,50.38,50.39,50.38,50.38,50.38,50.39,50.47,50.48,50.44,50.42,50.45,50.39,50.44,50.37,50.32,null,null,null,null,null,null,null,null,50.34,50.37,50.37,50.37,50.39,50.4,50.4,50.46,50.44,50.39,50.33,null,null,50.47,50.41,50.36,50.37,50.42,50.35,50.39,50.42,50.42,50.44,50.34,null,null,null,50.36,50.38,50.39,50.39,50.39,50.39,50.4,50.39,50.41,50.4,50.34,null,null,null,null,50.4,50.41,50.38,50.35,50.38,50.4,50.36,50.36,50.36,50.37,50.38,50.35,50.33,50.39,50.38,50.39,50.4,50.44,50.45,50.41,50.32,null,null,null,null,null,null,null,50.43,50.36,50.36,50.38,50.38,50.38,50.41,50.36,50.37,50.37,50.38,50.39,50.42,50.4,50.38,50.37,50.37,50.33,50.37,50.4,50.42,50.41,50.37,50.38,50.35,50.38,50.38,50.39,50.39,50.43,50.42,50.39,50.38,50.41,50.41,50.38,50.38,50.37,50.36,50.36,50.36,50.43,50.37,50.39,50.37,50.38,50.36,50.37,50.43,50.43,50.45,50.44,50.41,50.38,50.39,50.4,50.4,50.39,50.39,50.4,50.46,50.37,50.46,50.4,50.39,50.39,50.37,50.42,50.34,50.45,50.41,50.42,50.4,50.39,50.39,50.41,50.38,50.35,50.39,50.3,null,null,null,null,null,50.38,50.39,50.4,50.41,50.41,50.4,50.41,50.41,50.4,50.38,50.4,50.41,50.39,50.38,50.37,50.41,50.38,50.41,50.44,50.45,50.41,50.33,null,null,null,null,null,null,null,null,null,null,null,null,null,null,null,null,null,null,null,null,null,null,null,null,null,null,null,null,null,null,null,null,null,null,null,null,null,null,null,null,null,null,null,null,null,null,null,null,null,null,null,null,null,null,null,null,null,null,null,null,null,null,null,null,null,null,null,null,null,null,null,null,null,null,null,null,null,null,null,null,null,null,null,null,null,null,null,null,null,null,null,null,null,null,null,null,null,null]},{"y":2015,"min":[null,null,null,null,null,null,null,null,null,null,null,null,null,null,null,null,null,null,null,null,null,null,null,null,null,null,null,null,null,null,null,null,null,null,null,null,null,null,null,null,null,null,null,null,null,null,null,null,null,null,null,null,null,null,null,null,null,50.32,50.3,50.31,50.3,50.3,50.34,50.3,50.32,50.3,50.29,50.31,50.33,50.34,50.29,50.26,50.28,50.26,50.27,50.29,50.28,50.25,50.29,50.29,50.24,50.32,50.3,50.27,50.31,50.3,50.31,50.32,50.36,50.29,50.36,50.36,50.33,50.31,50.32,50.34,50.34,50.33,50.31,50.33,50.33,50.29,50.35,49.7,49.7,49.7,49.7,49.7,49.7,49.7,50.32,50.33,50.29,50.3,50.29,50.32,50.32,50.34,50.3,50.3,50.31,50.31,50.28,50.32,50.27,50.3,50.3,50.28,50.3,50.29,50.28,50.29,50.32,50.3,50.3,50.3,50.31,50.28,50.32,50.29,50.3,50.3,50.31,50.31,50.31,50.33,50.31,50.31,50.28,50.33,50.31,50.29,50.29,50.33,50.27,50.26,50.29,50.31,50.3,50.31,50.27,50.25,50.26,50.32,50.32,50.3,50.31,50.31,50.3,50.31,50.32,50.29,50.29,50.32,50.29,50.29,50.3,50.3,50.3,50.3,50.26,50.24,50.26,50.29,50.32,50.32,50.34,50.32,50.35,50.35,50.31,50.26,50.29,50.31,50.29,50.3,50.31,50.29,50.32,50.32,50.32,50.31,50.31,50.3,50.27,50.31,50.3,50.3,50.33,50.33,50.31,50.3,50.3,50.33,50.3,50.31,50.28,50.29,50.31,50.34,50.31,50.33,50.35,50.33,50.26,50.29,50.33,50.33,50.34,50.31,50.32,50.31,50.32,50.28,50.27,50.3,50.31,50.3,50.3,50.33,50.28,50.32,50.33,50.34,50.33,50.31,50.32,50.36,50.31,50.34,50.32,50.29,50.29,50.27,50.28,50.32,50.34,50.33,50.32,50.31,50.29,50.29,50.31,50.3,50.28,50.3,50.3,50.31,50.32,50.3,50.31,50.29,50.29,50.28,50.29,50.29,50.32,50.28,50.29,50.32,50.31,50.33,50.3,50.25,50.27,50.28,50.28,50.29,50.3,50.33,50.34,50.3,50.31,50.32,50.33,50.33,50.31,50.33,50.3,50.3,50.28,50.32,50.3,50.29,50.33,50.32,50.33,50.32,50.31,50.32,50.33,50.32,50.33,50.39,50.33,50.31,50.3,50.36,50.35,50.33,50.35,50.31,null,null,null,null,null,50.3,50.34,50.35,50.32,50.33,50.32,50.31,50.32,50.35,50.33,50.33,null,null,50.32,50.32,50.33,50.32,50.33,50.33,50.31,50.29,50.3,50.29,50.34,50.33,50.31,50.31,50.33,50.36,50.35,50.3,50.32,50.35,50.32,50.26,50.23,50.29,50.3],"max":[null,null,null,null,null,null,null,null,null,null,null,null,null,null,null,null,null,null,null,null,null,null,null,null,null,null,null,null,null,null,null,null,null,null,null,null,null,null,null,null,null,null,null,null,null,null,null,null,null,null,null,null,null,null,null,null,null,50.4,50.39,50.43,50.47,50.43,50.42,50.44,50.45,50.41,50.48,50.39,50.41,50.41,50.4,50.39,50.38,50.36,50.38,50.39,50.38,50.38,50.38,50.4,50.35,50.43,50.41,50.37,50.42,50.45,50.38,50.5,50.5,50.57,50.45,50.45,50.44,50.43,50.43,50.42,50.46,50.44,50.41,50.43,50.44,50.42,50.45,50.41,49.7,49.7,49.7,49.7,49.7,50.43,50.42,50.42,50.42,50.39,50.39,50.44,50.45,50.44,50.4,50.41,50.42,50.42,50.37,50.43,50.53,50.42,50.42,50.37,50.43,50.43,50.36,50.42,50.41,50.4,50.38,50.39,50.4,50.36,50.44,50.38,50.48,50.46,50.39,50.41,50.46,50.41,50.45,50.41,50.39,50.44,50.39,50.42,50.43,50.44,50.38,50.37,50.42,50.42,50.43,50.39,50.37,50.37,50.35,50.43,50.42,50.39,50.42,50.4,50.42,50.42,50.42,50.38,50.41,50.42,50.44,50.39,50.39,50.41,50.4,50.4,50.39,50.34,50.37,50.4,50.47,50.43,50.44,50.4,50.45,50.46,50.43,50.37,50.4,50.43,50.42,50.43,50.44,50.4,50.43,50.42,50.43,50.45,50.4,50.4,50.37,50.49,50.47,50.42,50.43,50.43,50.45,50.39,50.38,50.42,50.38,50.45,50.4,50.39,50.41,50.43,50.46,50.43,50.45,50.42,50.4,50.44,50.43,50.41,50.44,50.5,50.42,50.43,50.41,50.42,50.38,50.42,50.42,50.38,50.41,50.43,50.38,50.42,50.46,50.48,50.45,50.39,50.45,50.46,50.47,50.43,50.42,50.41,50.4,50.39,50.37,50.4,50.41,50.42,50.39,50.41,50.4,50.38,50.48,50.39,50.37,50.38,50.38,50.46,50.39,50.44,50.47,50.41,50.39,50.39,50.4,50.38,50.41,50.38,50.37,50.46,50.4,50.43,50.38,50.37,50.37,50.35,50.38,50.4,50.47,50.42,50.43,50.43,50.4,50.43,50.42,50.43,50.41,50.45,50.39,50.4,50.37,50.41,50.39,50.37,50.44,50.42,50.43,50.41,50.41,50.42,50.43,50.45,50.47,50.48,50.46,50.43,50.43,50.45,50.51,50.42,50.44,50.53,null,null,null,null,null,50.41,50.46,50.45,50.42,50.47,50.49,50.49,50.42,50.44,50.41,50.43,null,null,50.42,50.41,50.46,50.42,50.47,50.45,50.53,50.39,50.41,50.41,50.44,50.44,50.42,50.39,50.44,50.46,50.46,50.41,50.38,50.42,50.44,50.39,50.36,50.39,50.37]},{"y":2016,"min":[50.32,50.24,50.23,50.25,50.26,50.25,50.25,50.27,50.31,50.3,50.28,50.32,50.32,50.3,50.29,50.34,50.3,50.29,50.31,50.34,50.31,50.29,50.3,50.32,50.33,50.31,50.37,50.33,50.35,50.35,50.34,50.33,50.37,50.36,50.34,50.33,50.33,50.3,50.32,50.27,50.33,50.31,50.31,50.28,50.29,50.3,50.32,50.3,50.33,50.32,50.34,50.34,50.37,50.34,50.34,50.33,50.35,50.33,50.34,50.32,50.3,50.31,50.3,50.28,50.33,50.34,50.33,50.32,50.28,50.31,50.32,50.31,50.29,50.3,50.31,50.28,50.32,50.32,50.32,50.33,50.31,50.31,50.3,50.29,50.3,50.32,50.31,50.29,50.32,50.3,50.29,50.31,50.29,50.31,50.32,50.3,50.33,50.32,50.3,50.3,50.3,50.29,50.3,50.31,50.31,50.31,50.31,50.34,50.34,50.34,50.3,50.3,50.33,50.35,50.36,50.33,50.35,50.36,50.36,50.32,50.35,50.34,50.3,50.3,50.31,50.28,50.26,50.26,50.23,50.22,50.24,50.23,50.26,50.28,50.34,50.35,50.34,50.32,50.31,50.29,50.31,50.28,50.29,50.31,50.3,50.31,50.33,50.31,50.27,50.29,50.31,50.3,50.36,50.33,50.3,50.33,50.33,50.32,50.3,50.33,50.33,50.3,50.28,50.31,50.31,50.33,50.31,50.29,50.3,50.31,50.34,50.33,50.33,50.32,50.28,50.32,50.33,50.31,50.34,50.34,50.33,50.32,50.31,50.32,50.3,50.31,50.31,50.34,50.3,50.28,50.34,50.33,50.36,50.32,50.3,50.33,50.33,50.31,50.33,50.35,50.32,50.3,50.32,50.32,50.32,50.35,50.33,50.32,50.32,50.32,50.34,50.35,50.33,50.33,50.31,50.31,50.34,50.32,50.32,50.32,50.33,50.32,50.32,50.31,50.3,50.31,50.32,50.33,50.31,50.28,50.28,50.28,50.3,50.32,50.35,50.32,50.3,50.31,50.33,50.31,50.34,50.33,50.32,50.31,50.35,50.34,50.33,50.32,50.35,50.33,50.3,50.28,50.33,50.3,50.35,50.34,50.3,50.3,50.27,50.3,50.34,50.34,50.36,50.34,50.32,50.32,50.32,50.32,50.32,50.36,50.31,50.34,50.3,50.34,50.3,50.33,50.35,50.31,50.34,50.33,50.31,50.33,50.34,50.3,50.33,50.32,50.28,50.26,50.29,50.32,50.31,50.3,50.29,50.33,50.32,50.32,50.31,50.3,50.29,50.29,50.31,50.33,50.32,50.29,50.3,50.32,50.31,50.27,50.28,50.28,50.32,50.31,50.33,50.29,50.28,50.26,50.26,50.28,50.33,50.32,50.31,50.33,50.32,50.31,50.3,50.33,50.31,50.32,50.3,50.29,50.33,50.36,50.33,50.31,50.32,50.37,50.33,50.31,50.32,50.32,50.29,50.29,50.33,50.34,50.33,50.33,50.3,50.3,50.3,50.27,50.29,50.31,50.34,50.33,50.28,50.32,50.33,50.34,50.35,50.38,50.38,50.35,50.31,50.3,50.32,50.32],"max":[50.35,50.41,50.37,50.36,50.36,50.36,50.36,50.49,50.4,50.42,50.42,50.43,50.48,50.38,50.41,50.48,50.48,50.4,50.4,50.45,50.38,50.37,50.41,50.41,50.47,50.48,50.45,50.45,50.45,50.52,50.48,50.5,50.55,50.47,50.45,50.45,50.43,50.41,50.48,50.47,50.44,50.46,50.4,50.39,50.43,50.41,50.4,50.38,50.42,50.45,50.44,50.47,50.47,50.48,50.44,50.43,50.43,50.41,50.44,50.41,50.42,50.44,50.46,50.38,50.42,50.47,50.41,50.41,50.36,50.38,50.4,50.4,50.41,50.38,50.4,50.4,50.42,50.44,50.43,50.46,50.45,50.41,50.41,50.4,50.39,50.4,50.44,50.39,50.45,50.44,50.37,50.39,50.39,50.42,50.43,50.37,50.42,50.44,50.42,50.39,50.39,50.38,50.43,50.42,50.41,50.43,50.44,50.46,50.45,50.47,50.43,50.39,50.44,50.44,50.49,50.45,50.45,50.47,50.47,50.42,50.46,50.45,50.42,50.42,50.38,50.38,50.39,50.38,50.36,50.37,50.4,50.35,50.38,50.4,50.41,50.46,50.43,50.41,50.39,50.39,50.42,50.38,50.41,50.41,50.43,50.41,50.42,50.4,50.41,50.49,50.43,50.42,50.47,50.42,50.4,50.43,50.44,50.42,50.42,50.42,50.43,50.42,50.38,50.4,50.39,50.45,50.4,50.39,50.42,50.41,50.42,50.43,50.46,50.45,50.38,50.44,50.44,50.45,50.43,50.45,50.46,50.42,50.4,50.41,50.42,50.4,50.55,50.44,50.4,50.38,50.43,50.44,50.48,50.43,50.42,50.43,50.44,50.39,50.47,50.44,50.43,50.39,50.39,50.4,50.41,50.41,50.45,50.42,50.45,50.42,50.43,50.44,50.43,50.43,50.4,50.41,50.43,50.42,50.42,50.4,50.43,50.42,50.46,50.4,50.41,50.45,50.38,50.42,50.42,50.43,50.39,50.35,50.41,50.43,50.49,50.42,50.38,50.4,50.43,50.41,50.47,50.45,50.41,50.41,50.43,50.45,50.43,50.46,50.47,50.4,50.41,50.42,50.43,50.4,50.44,50.43,50.4,50.39,50.41,50.42,50.44,50.44,50.44,50.42,50.43,50.46,50.49,50.43,50.42,50.44,50.39,50.46,50.45,50.4,50.41,50.44,50.46,50.44,50.43,50.44,50.39,50.43,50.43,50.48,50.43,50.42,50.38,50.37,50.4,50.4,50.4,50.4,50.4,50.44,50.41,50.4,50.4,50.4,50.43,50.39,50.4,50.45,50.41,50.4,50.43,50.45,50.49,50.35,50.37,50.42,50.38,50.4,50.42,50.38,50.39,50.36,50.37,50.38,50.43,50.44,50.48,50.43,50.44,50.45,50.39,50.41,50.4,50.41,50.41,50.43,50.41,50.44,50.44,50.41,50.45,50.49,50.44,50.39,50.41,50.49,50.39,50.43,50.43,50.45,50.45,50.47,50.51,50.39,50.4,50.36,50.39,50.4,50.53,50.42,50.38,50.41,50.41,50.42,50.43,50.43,50.46,50.5,50.41,50.4,50.43,50.39]},{"y":2017,"min":[50.32,50.33,50.35,50.35,50.29,50.3,50.31,50.3,50.3,50.31,50.29,null,50.34,50.32,50.34,50.32,50.32,50.29,50.3,50.31,50.29,50.3,50.31,50.3,50.26,50.29,50.29,50.29,50.31,50.28,50.3,50.29,50.3,50.31,50.32,50.3,50.31,50.27,50.26,50.28,50.25,50.26,50.25,50.26,50.27,50.32,50.31,50.33,50.31,50.31,50.33,50.31,50.31,50.31,50.32,50.3,50.31,50.33,50.33,50.32,50.33,50.33,50.31,50.31,50.31,50.32,50.31,50.31,50.3,50.29,50.28,50.33,50.36,50.35,50.32,50.31,50.29,50.29,50.33,50.33,50.28,50.29,50.3,50.32,50.31,50.32,50.33,50.3,50.31,50.32,50.31,50.32,50.32,50.28,50.32,50.34,50.34,50.32,50.29,50.32,50.33,50.33,50.33,50.3,50.31,50.35,50.33,50.33,50.3,50.3,50.31,50.34,50.33,50.31,50.32,50.3,50.3,50.31,50.31,50.21,50.25,50.3,50.3,50.29,50.31,50.23,50.3,50.3,50.31,50.29,50.24,50.29,50.32,50.31,50.32,50.29,50.28,50.3,50.29,50.33,50.3,50.29,null,50.31,50.31,50.29,50.26,50.29,50.3,50.31,50.32,50.27,50.27,50.28,50.31,50.3,50.29,50.32,50.28,50.29,50.31,50.3,50.32,50.33,50.28,50.28,50.3,50.3,50.29,50.3,50.32,50.29,50.28,50.35,50.33,50.32,50.33,50.27,50.26,50.3,50.34,50.32,50.34,50.32,50.31,50.28,50.27,50.29,50.31,50.31,50.33,50.33,50.29,50.29,50.29,50.3,50.28,50.31,50.27,50.25,50.32,50.31,50.29,50.31,50.3,50.3,50.3,50.3,50.32,50.31,50.3,50.3,50.3,50.31,50.3,50.32,50.33,50.3,50.32,50.29,50.3,50.27,50.3,50.35,50.32,50.3,50.32,50.34,50.33,50.31,50.34,50.31,50.33,50.32,50.29,50.3,50.32,50.3,50.34,50.31,50.3,50.28,50.33,50.31,50.29,50.31,50.32,50.29,50.32,50.3,50.31,50.31,50.3,50.29,50.34,50.31,50.32,50.32,50.31,50.3,50.32,50.33,50.32,50.3,50.3,50.29,50.28,50.29,50.3,50.3,50.29,50.29,50.31,50.32,50.32,50.32,50.33,50.35,50.35,50.35,50.34,50.34,50.32,50.32,50.33,50.32,50.31,50.31,50.33,50.33,50.29,50.28,50.28,50.3,50.32,50.34,50.32,50.32,50.31,50.33,50.37,50.34,50.34,50.33,50.31,50.3,50.28,50.3,50.32,50.34,50.32,50.32,50.35,50.35,50.33,50.33,50.34,50.33,50.32,50.32,50.3,50.33,50.35,50.3,50.33,50.3,50.29,50.31,50.36,50.37,50.32,50.33,50.31,50.31,50.32,50.33,50.34,50.31,50.34,50.34,50.32,50.35,50.31,50.29,50.28,50.29,50.3,50.31,50.29,50.31,50.31,50.3,50.3,50.3,50.32,50.32,50.36,50.36,50.34,50.32,50.28,50.33,50.3,50.3,null],"max":[50.36,50.47,50.49,50.5,50.38,50.41,50.42,50.39,50.38,50.4,50.37,null,50.46,50.47,50.41,50.4,50.45,50.38,50.38,50.39,50.37,50.38,50.44,50.45,50.37,50.36,50.38,50.39,50.4,50.41,50.4,50.38,50.39,50.4,50.4,50.39,50.4,50.33,50.35,50.36,50.36,50.37,50.33,50.34,50.38,50.41,50.4,50.49,50.42,50.39,50.46,50.45,50.54,50.42,50.43,50.41,50.42,50.43,50.5,50.44,50.5,50.4,50.41,50.45,50.43,50.4,50.42,50.46,50.47,50.38,50.39,50.43,50.45,50.44,50.43,50.48,50.52,50.45,50.43,50.44,50.37,50.38,50.39,50.42,50.39,50.42,50.45,50.46,50.41,50.43,50.42,50.43,50.43,50.42,50.47,50.43,50.47,50.4,50.41,50.45,50.46,50.45,50.45,50.41,50.46,50.43,50.42,50.49,50.42,50.38,50.46,50.44,50.44,50.46,50.48,50.39,50.4,50.39,50.42,50.38,50.41,50.41,50.41,50.38,50.4,50.39,50.41,50.43,50.39,50.4,50.36,50.4,50.43,50.42,50.42,50.37,50.44,50.43,50.42,50.44,50.4,50.39,null,50.4,50.39,50.42,50.38,50.41,50.42,50.46,50.44,50.39,50.39,50.37,50.47,50.4,50.4,50.45,50.45,50.41,50.41,50.4,50.55,50.45,50.44,50.37,50.44,50.41,50.37,50.39,50.42,50.4,50.45,50.45,50.44,50.44,50.49,50.38,50.36,50.46,50.44,50.42,50.43,50.42,50.42,50.36,50.39,50.38,50.39,50.38,50.43,50.45,50.41,50.41,50.41,50.4,50.4,50.4,50.44,50.4,50.41,50.42,50.4,50.46,50.42,50.46,50.43,50.42,50.47,50.44,50.45,50.39,50.42,50.45,50.43,50.46,50.42,50.46,50.4,50.37,50.41,50.39,50.42,50.44,50.4,50.42,50.42,50.5,50.47,50.42,50.5,50.45,50.43,50.43,50.37,50.43,50.41,50.39,50.43,50.39,50.4,50.37,50.44,50.46,50.39,50.38,50.41,50.37,50.45,50.41,50.39,50.39,50.39,50.39,50.43,50.48,50.4,50.4,50.37,50.39,50.39,50.39,50.4,50.37,50.39,50.36,50.38,50.38,50.39,50.38,50.39,50.37,50.44,50.42,50.43,50.43,50.44,50.57,50.43,50.41,50.43,50.41,50.4,50.41,50.45,50.41,50.41,50.38,50.47,50.42,50.39,50.36,50.38,50.37,50.39,50.44,50.44,50.42,50.4,50.44,50.48,50.52,50.41,50.4,50.4,50.4,50.36,50.4,50.43,50.43,50.39,50.4,50.42,50.45,50.43,50.4,50.41,50.43,50.4,50.41,50.4,50.49,50.46,50.43,50.46,50.46,50.41,50.41,50.42,50.47,50.44,50.47,50.43,50.42,50.4,50.44,50.44,50.44,50.48,50.47,50.44,50.47,50.48,50.38,50.44,50.45,50.4,50.42,50.42,50.42,50.41,50.4,50.42,50.41,50.41,50.41,50.48,50.44,50.41,50.4,50.38,50.45,50.42,50.39,null]},{"y":2018,"min":[null,null,null,null,null,50.32,50.28,50.23,50.25,50.32,50.32,50.32,50.29,50.29,50.3,50.32,50.31,50.29,50.31,50.33,50.32,50.28,50.31,50.32,50.27,50.28,50.3,50.34,50.38,50.32,50.29,50.31,50.31,50.31,50.32,50.28,50.28,50.29,50.29,50.29,50.3,50.31,50.34,50.3,50.27,50.27,50.31,50.28,50.29,50.32,50.3,50.29,50.3,50.28,50.25,50.29,50.3,50.3,50.26,50.21,50.25,50.29,50.29,50.32,50.31,50.3,50.32,50.3,50.28,50.32,50.34,50.33,50.3,50.2,50.21,50.18,50.12,50.23,50.31,50.33,50.32,50.31,50.31,50.33,50.32,50.29,50.26,50.27,50.24,50.28,50.31,50.3,50.3,50.31,50.32,50.25,50.25,50.29,50.29,50.26,50.25,50.27,50.3,50.33,50.3,50.33,50.32,50.28,50.25,50.27,50.33,50.33,50.36,50.34,50.32,50.32,50.28,50.31,50.3,50.3,50.32,50.29,50.28,50.29,50.27,50.29,50.27,50.25,50.25,50.28,50.31,50.27,50.25,50.27,50.28,50.3,50.32,50.31,50.29,50.28,50.26,50.28,50.27,50.24,50.26,50.26,50.29,50.28,50.26,50.31,50.3,50.32,50.32,50.33,50.32,50.31,50.27,50.28,50.31,50.32,50.33,50.32,50.32,50.34,50.31,50.3,50.31,50.33,50.32,50.3,50.31,50.32,50.35,50.32,50.31,50.3,50.31,50.26,50.26,50.29,50.24,50.26,50.27,50.31,50.3,50.32,50.3,50.33,50.32,50.34,50.35,50.33,50.32,50.32,50.31,50.31,50.33,50.34,50.33,50.32,50.3,50.32,50.34,50.34,50.33,50.3,50.28,50.27,50.29,50.3,50.33,50.3,50.3,50.28,50.31,50.32,50.33,50.29,50.31,50.34,50.28,50.33,50.32,50.3,50.3,50.32,50.31,50.29,50.33,50.33,50.33,50.34,50.32,50.33,50.35,50.34,50.32,50.35,50.34,50.3,50.3,50.35,50.32,50.33,50.31,50.34,50.33,50.31,50.32,50.33,50.3,50.34,50.35,50.34,50.31,50.3,50.31,50.32,50.29,50.33,50.31,50.33,50.31,50.32,50.33,50.29,50.36,50.31,50.31,50.32,50.31,50.29,50.3,50.34,50.32,50.34,50.31,50.26,50.28,50.31,50.31,50.29,50.26,50.29,50.29,50.29,50.3,50.32,50.33,50.32,50.32,50.31,50.3,50.31,50.32,50.34,50.34,50.35,50.31,50.31,50.29,50.27,50.27,null,null,null,null,null,null,null,null,50.31,null,null,null,null,50.34,50.3,50.3,50.26,50.26,50.3,50.27,50.22,50.27,50.27,50.3,50.29,50.3,50.3,50.32,50.29,50.3,50.3,50.31,50.31,50.33,50.32,50.29,50.29,50.34,50.35,50.34,50.39,50.32,50.3,50.28,50.27,50.27,50.28,50.3,50.27,50.28,50.29,50.31,50.33,50.33,50.35,50.37,50.37,50.33,50.33,50.33,50.36,50.32],"max":[null,null,null,null,null,50.41,50.36,50.33,50.37,50.41,50.41,50.4,50.38,50.36,50.43,50.46,50.47,50.57,50.41,50.42,50.41,50.41,50.4,50.41,50.41,50.38,50.39,50.46,50.48,50.4,50.4,50.4,50.4,50.39,50.41,50.37,50.37,50.37,50.36,50.37,50.4,50.41,50.44,50.38,50.39,50.35,50.41,50.37,50.39,50.4,50.38,50.39,50.38,50.42,50.36,50.38,50.47,50.41,50.37,50.37,50.34,50.35,50.36,50.4,50.4,50.4,50.43,50.44,50.37,50.41,50.42,50.47,50.39,50.35,50.3,50.29,50.28,50.37,50.42,50.41,50.46,50.46,50.38,50.41,50.43,50.38,50.33,50.44,50.34,50.38,50.41,50.38,50.41,50.38,50.47,50.37,50.35,50.36,50.37,50.38,50.34,50.36,50.42,50.44,50.4,50.46,50.43,50.37,50.37,50.41,50.42,50.41,50.49,50.45,50.46,50.43,50.39,50.43,50.39,50.42,50.44,50.44,50.4,50.38,50.4,50.38,50.4,50.39,50.36,50.42,50.39,50.35,50.37,50.39,50.39,50.39,50.44,50.41,50.4,50.39,50.39,50.38,50.39,50.38,50.36,50.37,50.4,50.4,50.36,50.48,50.4,50.42,50.41,50.41,50.43,50.39,50.4,50.37,50.41,50.4,50.4,50.41,50.4,50.44,50.4,50.42,50.4,50.44,50.44,50.39,50.4,50.47,50.42,50.4,50.39,50.39,50.44,50.38,50.37,50.39,50.34,50.39,50.37,50.39,50.37,50.38,50.4,50.4,50.39,50.42,50.42,50.41,50.42,50.42,50.36,50.39,50.4,50.42,50.45,50.39,50.44,50.38,50.42,50.41,50.42,50.46,50.4,50.42,50.42,50.41,50.42,50.4,50.39,50.41,50.38,50.39,50.39,50.39,50.41,50.41,50.43,50.5,50.4,50.39,50.38,50.42,50.39,50.39,50.4,50.41,50.44,50.42,50.39,50.41,50.43,50.49,50.43,50.43,50.42,50.46,50.4,50.45,50.41,50.44,50.4,50.44,50.43,50.4,50.4,50.45,50.42,50.43,50.47,50.45,50.42,50.41,50.4,50.41,50.4,50.45,50.42,50.44,50.4,50.45,50.44,50.41,50.53,50.41,50.4,50.4,50.39,50.37,50.38,50.43,50.4,50.45,50.38,50.37,50.35,50.41,50.39,50.37,50.36,50.36,50.43,50.36,50.37,50.45,50.4,50.4,50.42,50.39,50.35,50.39,50.38,50.5,50.46,50.45,50.4,50.43,50.38,50.36,50.35,null,null,null,null,null,null,null,null,50.37,null,null,null,null,50.4,50.39,50.38,50.36,50.35,50.37,50.4,50.32,50.37,50.37,50.43,50.36,50.44,50.41,50.39,50.39,50.38,50.39,50.39,50.41,50.43,50.47,50.43,50.4,50.41,50.44,50.47,50.47,50.43,50.36,50.36,50.35,50.36,50.36,50.37,50.41,50.36,50.38,50.49,50.45,50.42,50.42,50.41,50.41,50.46,50.46,50.43,50.48,50.38]},{"y":2019,"min":[50.38,50.32,50.31,50.32,50.31,50.3,50.34,50.35,50.32,50.31,50.33,50.37,50.38,50.36,50.37,50.32,50.34,50.31,50.3,50.3,50.31,50.29,50.28,50.29,50.29,50.31,50.31,50.32,50.33,50.29,50.3,50.27,50.3,50.34,50.33,50.34,50.32,50.32,50.32,50.34,50.31,50.35,50.34,50.34,50.31,50.29,50.3,50.3,50.3,50.31,50.31,50.32,50.28,50.28,50.31,50.3,50.31,50.31,50.32,50.31,50.29,50.33,50.33,50.34,50.29,50.32,50.33,50.32,50.31,50.35,50.32,50.35,50.31,50.32,50.34,50.34,50.34,50.31,50.31,50.32,50.31,50.33,50.33,50.32,50.32,50.32,50.33,50.31,50.3,50.3,50.28,50.3,50.32,50.34,50.34,50.29,50.3,50.3,50.29,50.31,50.3,50.29,50.28,50.28,50.29,50.26,50.25,50.26,50.28,50.31,50.3,50.24,50.19,50.25,50.3,50.31,50.29,50.31,50.34,50.3,50.35,50.36,50.3,50.31,50.31,50.33,50.3,50.28,50.31,50.33,50.29,50.35,50.35,50.31,50.32,50.32,50.29,50.3,50.31,50.36,50.38,50.34,50.34,50.33,50.28,50.3,50.35,50.35,50.33,50.33,50.35,50.32,50.31,50.3,50.32,50.32,50.32,50.26,50.3,50.33,50.35,50.35,50.32,50.33,50.3,50.32,50.33,50.3,50.32,50.31,50.35,50.34,50.28,50.3,50.28,50.3,50.32,50.31,50.31,50.27,50.31,50.35,50.33,50.32,50.32,50.3,50.33,50.35,50.37,50.34,50.31,50.32,50.32,50.34,50.32,50.33,50.34,50.3,50.29,50.3,50.32,50.34,50.35,50.3,50.31,50.33,50.27,50.25,50.3,50.34,50.31,50.33,50.32,50.33,50.33,50.34,50.33,50.33,50.33,50.33,50.31,50.33,50.33,50.33,50.31,50.3,50.3,50.33,50.3,50.33,50.35,50.33,50.32,50.3,50.29,50.3,50.32,50.29,50.3,50.3,50.35,50.34,50.31,50.33,50.33,50.3,50.31,50.33,50.31,50.31,50.32,50.34,50.36,50.31,50.31,50.32,50.29,50.31,50.32,50.34,50.32,50.3,50.28,50.29,50.28,50.32,50.31,50.31,50.3,50.3,50.3,50.32,50.35,50.31,50.35,50.34,50.3,50.3,50.28,50.31,50.33,50.33,50.32,50.33,50.33,50.32,50.31,50.32,50.36,50.35,50.34,50.31,50.33,50.3,50.34,50.31,50.32,50.34,50.32,50.35,50.35,50.32,50.31,50.31,50.3,50.34,50.28,50.3,50.33,50.33,50.31,50.33,50.31,50.3,50.33,50.32,null,null,null,null,null,null,null,null,null,null,null,null,null,null,null,null,null,null,null,null,null,null,null,null,null,null,null,null,null,null,null,null,null,null,null,null,null,null,null,null,null,null,null,null,null,null,null,null,null],"max":[50.45,50.47,50.41,50.46,50.41,50.38,50.42,50.55,50.4,50.38,50.43,50.43,50.47,50.45,50.47,50.42,50.42,50.4,50.36,50.36,50.39,50.37,50.41,50.38,50.4,50.42,50.41,50.43,50.43,50.36,50.4,50.35,50.39,50.42,50.4,50.42,50.42,50.42,50.42,50.43,50.44,50.47,50.48,50.49,50.39,50.38,50.38,50.38,50.4,50.41,50.4,50.41,50.39,50.37,50.45,50.41,50.4,50.4,50.55,50.43,50.4,50.43,50.52,50.56,50.38,50.49,50.5,50.51,50.43,50.45,50.4,50.47,50.43,50.49,50.45,50.44,50.5,50.49,50.45,50.42,50.41,50.41,50.41,50.53,50.45,50.45,50.42,50.42,50.44,50.41,50.4,50.4,50.43,50.43,50.43,50.37,50.38,50.42,50.42,50.46,50.41,50.38,50.38,50.37,50.42,50.4,50.39,50.38,50.4,50.41,50.4,50.42,50.38,50.38,50.48,50.43,50.39,50.4,50.47,50.45,50.45,50.46,50.43,50.4,50.42,50.48,50.4,50.38,50.41,50.43,50.41,50.45,50.52,50.44,50.42,50.44,50.4,50.4,50.43,50.48,50.49,50.47,50.46,50.42,50.38,50.41,50.47,50.43,50.43,50.45,50.44,50.42,50.42,50.44,50.43,50.44,50.54,50.4,50.4,50.41,50.42,50.47,50.41,50.42,50.39,50.44,50.42,50.41,50.43,50.41,50.44,50.45,50.4,50.39,50.41,50.4,50.42,50.41,50.43,50.36,50.46,50.47,50.43,50.44,50.41,50.43,50.45,50.44,50.46,50.44,50.41,50.41,50.42,50.43,50.41,50.42,50.45,50.42,50.41,50.41,50.43,50.47,50.47,50.42,50.4,50.43,50.41,50.43,50.42,50.49,50.41,50.42,50.43,50.42,50.42,50.45,50.42,50.45,50.44,50.51,50.4,50.46,50.41,50.42,50.45,50.4,50.4,50.45,50.4,50.43,50.44,50.43,50.43,50.43,50.39,50.4,50.4,50.43,50.4,50.41,50.45,50.5,50.39,50.43,50.44,50.44,50.42,50.46,50.42,50.4,50.41,50.45,50.46,50.43,50.4,50.43,50.38,50.43,50.43,50.49,50.43,50.39,50.38,50.38,50.38,50.43,50.4,50.48,50.4,50.43,50.41,50.41,50.52,50.44,50.44,50.45,50.38,50.42,50.36,50.44,50.46,50.42,50.45,50.41,50.41,50.4,50.46,50.42,50.48,50.43,50.48,50.43,50.43,50.42,50.44,50.41,50.44,50.44,50.41,50.46,50.44,50.41,50.39,50.4,50.42,50.44,50.39,50.45,50.48,50.42,50.4,50.41,50.4,50.47,50.42,50.39,null,null,null,null,null,null,null,null,null,null,null,null,null,null,null,null,null,null,null,null,null,null,null,null,null,null,null,null,null,null,null,null,null,null,null,null,null,null,null,null,null,null,null,null,null,null,null,null,null]},{"y":2020,"min":[null,null,null,null,null,50.32,50.33,50.32,50.32,50.36,50.33,50.31,50.33,50.33,50.35,50.32,50.32,50.32,50.34,50.33,50.32,50.34,null,null,null,null,null,null,null,null,null,null,null,null,null,null,null,null,null,null,null,null,null,null,null,null,null,null,null,null,null,null,null,null,null,50.34,50.31,50.31,50.3,50.3,50.33,50.33,50.33,50.32,50.3,50.31,50.33,50.32,50.32,50.31,50.31,50.33,50.34,50.28,50.29,50.33,50.33,50.36,50.32,50.31,50.28,50.25,50.29,50.28,50.27,50.27,50.3,50.33,50.34,50.36,50.31,50.3,50.34,50.34,50.31,50.29,50.33,50.32,50.31,50.29,50.31,50.29,50.33,50.36,50.33,50.31,50.28,50.29,50.24,50.23,50.24,50.22,50.25,50.26,50.3,50.3,50.32,50.31,50.31,50.32,50.32,50.33,50.33,50.36,50.34,50.35,50.34,50.32,50.29,50.27,50.31,50.32,50.33,50.29,50.27,50.26,50.3,50.34,50.36,50.3,50.31,50.3,50.31,50.34,50.35,50.32,50.33,50.32,50.32,50.27,50.28,50.31,50.3,50.34,50.3,50.32,50.32,50.32,50.3,50.34,50.34,50.31,50.31,50.27,50.3,50.3,50.37,50.36,50.32,50.33,50.3,50.33,50.34,50.35,50.31,50.27,50.28,50.3,50.3,50.34,50.33,50.34,50.35,50.34,50.35,50.33,50.32,50.39,50.31,50.32,50.3,50.32,50.32,50.3,50.31,50.33,50.33,50.3,50.31,50.31,50.3,50.32,50.34,50.29,50.31,50.33,50.32,50.33,50.3,50.31,50.34,50.31,50.32,50.3,50.34,50.35,50.33,50.33,50.32,50.3,50.33,50.32,50.3,50.29,50.29,50.3,50.32,50.3,50.3,50.32,50.34,50.32,50.31,50.3,50.32,50.36,50.33,50.29,50.32,50.31,50.3,50.33,50.32,50.35,50.3,50.32,50.31,50.35,50.32,50.36,50.35,50.34,50.3,50.33,50.33,50.33,50.35,50.33,50.33,50.34,50.3,50.32,50.31,50.35,50.36,50.33,50.33,50.33,50.32,50.31,50.33,50.33,50.33,50.3,50.31,50.25,50.25,50.28,50.31,50.33,50.31,50.32,50.33,50.33,50.34,50.35,50.3,50.32,50.32,50.34,50.33,50.36,50.34,50.32,50.32,50.33,50.3,50.3,50.31,50.35,50.33,50.32,50.33,50.33,50.31,50.32,50.36,50.32,50.32,50.32,50.32,50.32,50.32,50.32,50.31,50.32,50.33,50.33,50.33,50.32,50.31,50.36,50.33,50.33,50.33,50.31,50.35,50.31,50.32,50.32,50.3,50.33,50.3,50.32,50.37,50.33,50.31,50.3,50.29,50.31,50.3,50.31,50.28,50.29,50.31,50.3,50.3,50.31,50.32,50.33,50.31,50.32,50.33,50.32,50.33,50.32,50.33,50.31,50.31,50.35,50.35,50.3,50.31,50.33,50.34,50.31],"max":[null,null,null,null,null,50.41,50.48,50.45,50.44,50.48,50.48,50.43,50.45,50.44,50.43,50.43,50.42,50.42,50.42,50.42,50.43,50.42,null,null,null,null,null,null,null,null,null,null,null,null,null,null,null,null,null,null,null,null,null,null,null,null,null,null,null,null,null,null,null,null,null,50.43,50.45,50.44,50.44,50.41,50.48,50.4,50.45,50.38,50.37,50.49,50.42,50.44,50.42,50.48,50.45,50.58,50.48,50.41,50.4,50.46,50.48,50.47,50.43,50.39,50.38,50.38,50.47,50.38,50.41,50.4,50.41,50.43,50.44,50.45,50.39,50.43,50.44,50.45,50.39,50.38,50.42,50.43,50.4,50.39,50.41,50.38,50.42,50.45,50.42,50.41,50.37,50.39,50.36,50.4,50.45,50.4,50.36,50.4,50.4,50.38,50.4,50.44,50.48,50.41,50.43,50.42,50.47,50.44,50.43,50.43,50.46,50.42,50.4,50.35,50.41,50.41,50.42,50.4,50.38,50.39,50.41,50.41,50.44,50.44,50.38,50.41,50.38,50.41,50.44,50.44,50.42,50.43,50.42,50.41,50.4,50.42,50.43,50.45,50.43,50.4,50.44,50.42,50.42,50.44,50.43,50.42,50.44,50.4,50.46,50.49,50.46,50.48,50.43,50.53,50.47,50.43,50.42,50.48,50.42,50.39,50.39,50.38,50.39,50.43,50.44,50.44,50.45,50.43,50.5,50.45,50.46,50.55,50.44,50.42,50.45,50.44,50.41,50.45,50.4,50.43,50.42,50.42,50.4,50.4,50.39,50.42,50.44,50.41,50.4,50.44,50.4,50.45,50.42,50.47,50.46,50.45,50.4,50.41,50.42,50.44,50.43,50.41,50.41,50.4,50.41,50.46,50.4,50.41,50.39,50.39,50.45,50.4,50.39,50.45,50.42,50.41,50.4,50.39,50.44,50.45,50.42,50.44,50.51,50.45,50.42,50.42,50.42,50.45,50.43,50.44,50.41,50.46,50.43,50.44,50.43,50.44,50.44,50.44,50.42,50.49,50.44,50.56,50.44,50.44,50.46,50.42,50.42,50.44,50.46,50.43,50.42,50.44,50.42,50.42,50.42,50.43,50.47,50.42,50.4,50.38,50.39,50.41,50.39,50.43,50.51,50.42,50.45,50.44,50.42,50.45,50.41,50.44,50.45,50.47,50.5,50.45,50.51,50.4,50.44,50.46,50.41,50.44,50.4,50.45,50.42,50.42,50.46,50.43,50.44,50.43,50.43,50.45,50.47,50.43,50.42,50.42,50.4,50.45,50.4,50.43,50.43,50.42,50.43,50.41,50.5,50.48,50.46,50.48,50.44,50.4,50.47,50.45,50.41,50.43,50.42,50.43,50.44,50.44,50.45,50.43,50.41,50.41,50.38,50.41,50.43,50.41,50.4,50.42,50.42,50.42,50.4,50.41,50.43,50.42,50.43,50.45,50.43,50.4,50.41,50.47,50.51,50.39,50.48,50.37,50.4,50.43,50.5,50.45,50.43,50.44]},{"y":2021,"min":[50.36,50.32,50.32,50.34,50.34,50.33,50.34,50.33,50.3,50.32,50.36,50.36,50.39,50.31,50.33,50.32,50.33,50.35,50.35,50.31,50.31,50.33,50.3,50.3,50.32,50.33,50.29,50.3,50.28,50.32,50.33,50.33,50.32,50.32,50.34,50.28,50.21,50.18,50.24,50.32,50.31,50.35,50.36,50.35,50.35,50.34,50.32,50.34,50.33,50.33,50.31,50.35,50.33,50.36,50.35,50.3,50.34,50.35,50.34,50.34,50.32,50.35,50.35,50.34,50.35,50.37,50.35,50.35,50.33,50.33,null,null,50.34,50.36,50.33,50.32,50.31,50.32,50.34,50.37,50.36,50.32,50.33,50.32,50.33,50.35,50.34,50.35,50.33,50.29,50.33,50.34,50.34,50.34,50.38,50.36,50.36,50.33,50.31,50.28,50.29,50.38,50.36,50.3,50.31,50.31,50.33,50.33,50.33,50.34,50.34,50.31,50.3,50.3,50.32,49.7,50.25,50.28,50.31,50.31,50.3,50.3,50.35,50.32,50.38,50.31,50.31,50.29,50.29,50.33,50.33,50.31,50.32,50.34,50.31,50.31,50.34,50.34,50.31,50.31,50.34,50.3,50.33,50.33,50.34,50.33,50.37,50.34,50.32,50.32,50.3,50.31,50.28,50.3,50.32,50.32,50.34,50.32,50.31,50.32,50.33,50.33,50.35,50.33,50.32,50.32,50.31,50.3,50.32,50.31,50.33,50.36,50.35,50.32,50.29,50.3,50.3,50.3,50.31,50.3,50.34,50.31,50.33,50.3,50.31,50.34,50.34,50.32,50.31,50.34,50.32,50.33,50.34,50.34,50.31,50.3,50.35,50.34,50.34,50.33,50.33,50.32,50.31,50.29,50.27,50.32,50.34,50.35,50.32,50.32,50.31,50.3,50.32,50.34,50.31,50.3,50.29,50.3,50.29,50.32,50.3,50.32,50.3,50.3,50.28,50.3,50.33,50.36,50.36,50.33,50.31,50.33,50.28,50.3,50.33,50.3,50.33,50.35,50.34,50.33,50.32,50.33,50.33,50.32,50.29,50.3,50.31,50.29,50.31,50.32,50.32,50.31,50.33,50.33,50.34,50.34,50.3,50.31,50.33,50.31,50.3,50.28,50.32,50.34,50.31,50.32,50.34,50.33,50.31,50.35,50.37,50.34,50.35,50.31,50.34,50.36,50.36,50.35,50.35,50.35,50.34,50.32,50.35,50.39,50.38,50.36,50.37,50.37,50.35,50.36,50.34,50.33,50.36,50.38,50.43,50.39,50.34,50.25,50.29,50.26,50.23,50.22,50.24,50.25,50.27,50.27,50.24,50.28,50.33,50.32,50.35,50.29,50.24,50.23,50.23,50.24,50.24,50.23,50.27,50.28,50.29,50.29,50.32,50.31,50.31,50.27,50.29,50.23,50.24,50.27,50.23,50.28,50.28,50.28,50.27,50.27,50.3,50.22,50.27,50.26,50.25,50.23,50.24,50.25,50.27,50.28,50.31,50.29,50.27,50.27,50.28,50.3,50.3,50.26,50.3,50.27,50.28,50.32,50.26,50.28,50.27,50.26,50.29,50.29,50.35],"max":[50.39,50.45,50.42,50.43,50.43,50.45,50.47,50.44,50.39,50.42,50.48,50.47,50.52,50.43,50.43,50.43,50.41,50.45,50.47,50.42,50.44,50.44,50.47,50.44,50.47,50.44,50.4,50.42,50.42,50.45,50.42,50.44,50.43,50.47,50.49,50.39,50.37,50.28,50.37,50.4,50.42,50.38,50.41,50.39,50.38,50.37,50.39,50.49,50.43,50.47,50.42,50.44,50.49,50.49,50.43,50.42,50.44,50.47,50.44,50.44,50.47,50.54,50.47,50.46,50.45,50.45,50.45,50.45,50.45,50.41,null,null,50.49,50.49,50.49,50.42,50.42,50.43,50.57,50.5,50.45,50.42,50.41,50.44,50.42,50.48,50.44,50.48,50.42,50.39,50.43,50.44,50.44,50.48,50.49,50.49,50.46,50.45,50.42,50.4,50.5,50.57,50.47,50.41,50.41,50.45,50.44,50.48,50.45,50.47,50.44,50.45,50.42,50.38,50.42,50.44,50.4,50.41,50.47,50.46,50.47,50.45,50.46,50.51,50.51,50.42,50.44,50.4,50.41,50.45,50.42,50.43,50.45,50.45,50.41,50.46,50.43,50.45,50.42,50.44,50.46,50.41,50.44,50.46,50.46,50.42,50.46,50.45,50.39,50.43,50.41,50.39,50.36,50.41,50.4,50.4,50.45,50.44,50.43,50.41,50.44,50.45,50.45,50.42,50.42,50.42,50.42,50.41,50.46,50.43,50.45,50.51,50.47,50.43,50.43,50.45,50.41,50.4,50.46,50.39,50.44,50.48,50.44,50.39,50.42,50.47,50.43,50.41,50.43,50.46,50.43,50.43,50.48,50.44,50.42,50.41,50.46,50.42,50.46,50.46,50.42,50.43,50.43,50.39,50.45,50.41,50.46,50.45,50.42,50.45,50.4,50.46,50.44,50.45,50.41,50.39,50.43,50.4,50.39,50.43,50.4,50.44,50.39,50.39,50.39,50.42,50.44,50.47,50.48,50.41,50.42,50.42,50.43,50.41,50.43,50.45,50.43,50.43,50.45,50.42,50.41,50.44,50.44,50.42,50.43,50.41,50.39,50.37,50.44,50.42,50.44,50.41,50.42,50.44,50.44,50.46,50.43,50.41,50.46,50.42,50.4,50.36,50.44,50.51,50.42,50.45,50.44,50.42,50.4,50.48,50.48,50.45,50.47,50.42,50.45,50.44,50.46,50.45,50.45,50.45,50.42,50.43,50.44,50.49,50.51,50.46,50.47,50.5,50.47,50.45,50.44,50.44,50.45,50.55,50.54,50.47,50.42,50.44,50.41,50.41,50.37,50.38,50.35,50.4,50.39,50.41,50.39,50.43,50.46,50.44,50.47,50.54,50.37,50.4,50.39,50.4,50.37,50.39,50.41,50.41,50.4,50.4,50.45,50.42,50.39,50.38,50.41,50.38,50.39,50.38,50.34,50.38,50.42,50.45,50.47,50.45,50.42,50.34,50.39,50.45,50.38,50.34,50.38,50.36,50.38,50.38,50.4,50.38,50.4,50.4,50.39,50.44,50.48,50.44,50.43,50.38,50.37,50.48,50.33,50.34,50.42,50.37,50.45,50.44,50.44]},{"y":2022,"min":[50.3,50.29,50.29,50.28,50.31,50.27,50.28,50.28,50.27,50.27,50.22,50.24,50.28,50.27,50.23,50.26,50.31,50.25,50.27,50.32,50.28,50.27,50.27,50.28,50.28,50.3,50.34,50.29,50.3,50.32,50.27,50.33,50.27,50.26,50.29,50.34,50.33,50.31,50.31,50.31,50.29,50.3,50.25,50.29,50.29,50.33,50.33,50.33,50.22,50.28,50.27,50.34,50.31,50.25,50.25,50.32,50.28,50.25,50.26,50.27,50.28,50.24,49.86,50.24,50.28,50.3,50.28,50.26,50.24,50.21,50.26,50.24,50.29,50.28,50.21,50.24,50.25,50.21,50.17,50.25,50.27,50.29,50.26,50.26,50.28,50.27,50.28,50.29,50.27,50.2,50.23,50.27,50.3,50.3,50.32,50.27,50.28,50.27,50.3,50.28,50.26,50.23,50.28,50.27,50.3,50.25,50.27,50.3,50.27,50.29,50.23,50.29,null,null,50.25,50.28,50.29,50.29,50.27,50.26,50.27,50.26,50.29,50.28,50.27,50.29,50.31,50.32,50.3,50.3,50.3,50.33,50.28,50.27,50.26,50.21,50.3,50.24,50.24,50.24,50.31,50.29,50.22,50.27,50.26,50.29,50.34,50.3,50.28,50.26,50.23,50.26,50.25,50.24,50.23,50.24,50.28,50.28,50.25,50.28,50.26,50.25,50.26,50.3,50.26,50.27,50.26,50.25,50.27,50.23,50.28,50.24,50.19,50.18,50.21,50.21,50.22,50.26,50.24,50.18,50.19,50.27,50.25,50.27,50.29,50.29,50.29,50.29,50.29,50.28,50.32,50.29,50.27,50.27,50.27,50.27,50.28,50.27,50.28,50.24,50.24,50.29,50.28,50.26,50.25,50.29,50.27,50.26,50.22,50.24,50.27,50.28,50.3,50.29,50.3,50.27,50.3,50.28,50.24,50.28,50.23,50.24,50.25,50.25,50.25,50.25,50.27,50.27,50.29,50.3,50.31,50.31,50.32,50.29,50.26,50.28,50.25,50.3,50.31,50.33,50.31,50.28,50.27,50.26,50.25,50.2,50.28,50.26,50.28,50.3,50.31,50.29,50.29,50.32,50.31,50.29,50.29,50.28,50.32,50.34,50.34,50.32,50.3,50.26,50.25,50.27,50.23,50.34,50.31,50.32,50.29,50.29,50.28,50.27,50.33,50.33,50.29,50.27,50.31,50.29,50.28,50.26,50.3,50.27,50.24,50.25,50.27,50.28,50.27,50.27,50.29,50.26,50.25,50.29,50.27,50.22,50.28,50.31,50.27,50.26,50.28,50.25,50.26,50.27,50.28,50.29,50.23,50.26,50.25,50.27,50.28,50.26,50.27,50.27,50.27,50.24,50.25,50.26,50.27,50.24,50.16,50.23,50.25,50.28,50.28,50.25,50.25,50.26,50.26,50.29,50.29,50.28,50.3,50.3,50.23,50.23,50.24,50.23,50.32,50.32,50.32,50.3,50.31,50.29,50.31,50.29,50.27,50.28,50.3,50.27,50.28,50.27,50.28,50.29,50.31,50.33,50.29,50.31,50.31,50.34,50.31,50.31,50.33,50.27,50.3],"max":[50.38,50.43,50.45,50.37,50.43,50.41,50.42,50.44,50.43,50.49,50.38,50.38,50.42,50.42,50.38,50.38,50.47,50.38,50.4,50.43,50.41,50.42,50.38,50.41,50.44,50.41,50.47,50.42,50.52,50.55,50.42,50.48,50.45,50.38,50.42,50.48,50.5,50.43,50.46,50.44,50.39,50.51,50.37,50.41,50.41,50.46,50.44,50.59,50.53,50.61,50.42,50.48,50.43,50.43,50.44,50.47,50.41,50.39,50.41,50.42,50.4,50.37,50.36,50.38,50.41,50.43,50.42,50.38,50.41,50.34,50.37,50.37,50.42,50.37,50.37,50.4,50.37,50.38,50.32,50.42,50.41,50.4,50.41,50.4,50.43,50.38,50.42,50.41,50.4,50.35,50.41,50.4,50.4,50.52,50.46,50.45,50.48,50.44,50.43,50.46,50.43,50.35,50.41,50.46,50.43,50.41,50.4,50.42,50.44,50.44,50.41,50.29,null,null,50.38,50.4,50.4,50.39,50.41,50.38,50.38,50.39,50.42,50.37,50.39,50.4,50.43,50.44,50.44,50.43,50.47,50.45,50.42,50.38,50.36,50.35,50.44,50.39,50.4,50.4,50.45,50.39,50.39,50.42,50.37,50.41,50.49,50.44,50.39,50.4,50.38,50.4,50.36,50.36,50.38,50.35,50.43,50.41,50.36,50.41,50.36,50.38,50.39,50.44,50.39,50.38,50.41,50.36,50.39,50.39,50.41,50.4,50.36,50.33,50.34,50.3,50.36,50.37,50.38,50.39,50.32,50.38,50.34,50.4,50.42,50.4,50.4,50.42,50.43,50.4,50.44,50.42,50.41,50.41,50.37,50.39,50.45,50.39,50.44,50.41,50.37,50.41,50.43,50.4,50.37,50.41,50.4,50.36,50.36,50.37,50.38,50.42,50.42,50.47,50.43,50.38,50.39,50.38,50.37,50.45,50.39,50.44,50.38,50.41,50.39,50.39,50.44,50.39,50.43,50.43,50.41,50.42,50.42,50.4,50.43,50.39,50.37,50.43,50.43,50.45,50.44,50.41,50.37,50.37,50.38,50.4,50.39,50.42,50.4,50.41,50.44,50.42,50.39,50.44,50.44,50.42,50.41,50.41,50.46,50.43,50.46,50.46,50.42,50.41,50.41,50.4,50.37,50.44,50.47,50.43,50.39,50.4,50.39,50.42,50.44,50.46,50.38,50.41,50.44,50.39,50.41,50.38,50.41,50.39,50.34,50.38,50.36,50.38,50.39,50.38,50.43,50.38,50.36,50.4,50.39,50.34,50.41,50.42,50.36,50.38,50.38,50.37,50.36,50.39,50.44,50.42,50.36,50.4,50.38,50.39,50.42,50.36,50.38,50.39,50.38,50.34,50.36,50.36,50.35,50.33,50.31,50.33,50.36,50.39,50.39,50.35,50.37,50.4,50.37,50.39,50.4,50.41,50.41,50.42,50.37,50.38,50.36,50.35,50.44,50.46,50.42,50.42,50.41,50.39,50.42,50.41,50.41,50.37,50.43,50.38,50.38,50.35,50.38,50.38,50.4,50.45,50.42,50.42,50.36,50.42,50.51,50.44,50.44,50.42,50.45]},{"y":2023,"min":[50.32,50.3,50.28,50.29,50.3,50.26,50.29,50.31,50.3,50.28,50.3,50.3,50.31,50.26,50.31,50.24,50.22,50.24,50.26,50.27,50.26,50.26,50.26,50.27,50.28,50.3,50.29,50.29,50.32,50.35,50.34,50.36,50.28,50.31,50.27,50.26,50.31,50.26,50.26,50.27,50.31,50.31,50.29,50.27,50.28,50.29,50.29,50.31,50.3,50.33,50.36,50.3,50.26,50.28,50.31,50.28,50.27,50.29,50.28,50.27,50.28,50.3,50.32,50.32,50.3,50.31,50.25,50.28,50.26,50.28,50.29,50.31,50.29,50.31,50.28,50.29,50.32,50.32,50.33,50.29,50.29,50.3,50.27,50.28,50.27,50.33,50.29,50.27,50.31,50.28,50.23,50.26,50.28,50.27,50.26,50.26,50.26,50.25,50.27,50.26,50.3,50.23,50.31,50.28,50.31,50.29,50.28,50.23,50.27,50.24,50.19,50.27,50.25,50.3,50.32,50.3,50.26,50.25,50.31,50.25,50.3,50.29,50.28,50.19,50.27,50.23,50.2,50.26,50.26,50.29,50.27,50.28,50.26,50.28,50.32,50.3,50.24,50.23,50.25,50.24,50.24,50.25,50.29,50.25,50.28,50.27,50.22,50.27,50.31,50.3,50.27,50.28,50.23,50.21,50.25,50.26,50.27,50.25,50.23,50.25,50.26,50.26,50.27,50.28,50.23,50.25,50.27,50.27,50.26,50.28,50.28,50.29,50.26,50.27,50.29,50.27,50.28,50.31,50.3,50.28,50.3,50.27,50.28,50.29,50.25,50.26,50.28,50.25,50.23,50.25,50.3,50.28,50.3,50.28,50.24,50.26,50.29,50.31,50.28,50.28,50.29,50.29,50.27,50.26,50.3,50.29,50.27,50.25,50.3,50.27,50.29,50.3,50.29,50.25,50.29,50.29,50.24,50.29,50.32,50.31,50.27,50.27,50.28,50.27,50.29,50.28,50.29,50.26,50.26,50.25,50.25,50.29,50.3,50.27,50.27,50.22,50.26,50.27,50.29,50.3,50.29,50.29,50.29,50.29,50.26,50.28,50.27,50.27,50.24,50.21,50.26,50.28,50.3,50.3,50.24,50.25,50.25,50.22,50.26,50.26,50.27,50.31,50.26,50.23,50.28,50.3,50.28,50.27,50.26,50.25,50.27,50.27,50.28,50.3,50.3,50.3,50.3,50.29,50.27,50.31,50.27,50.28,50.29,50.3,50.26,50.26,50.31,50.3,50.3,50.25,50.2,50.24,50.2,50.28,50.26,50.29,50.27,50.24,50.27,50.29,50.27,50.29,50.3,50.31,50.27,50.25,50.29,50.24,50.27,50.33,50.28,50.29,50.28,50.31,50.3,50.28,50.27,50.32,50.3,50.28,50.3,50.26,50.26,50.31,50.3,50.3,50.34,50.32,50.29,50.27,50.27,50.26,50.28,50.28,50.26,50.29,50.31,50.26,50.27,50.29,50.28,50.28,50.29,50.29,50.28,50.27,50.26,50.27,50.28,50.31,50.29,50.31,50.31,50.32,50.34,50.26,50.31,50.31,50.15,50.15,50.14,50.24,50.28,50.29,50.25],"max":[50.39,50.42,50.39,50.47,50.45,50.41,50.37,50.41,50.45,50.43,50.43,50.41,50.42,50.4,50.42,50.38,50.45,50.36,50.39,50.39,50.37,50.38,50.41,50.35,50.39,50.4,50.41,50.42,50.43,50.5,50.44,50.48,50.43,50.49,50.37,50.38,50.44,50.41,50.37,50.39,50.4,50.43,50.4,50.4,50.39,50.4,50.41,50.47,50.49,50.43,50.5,50.48,50.36,50.38,50.44,50.42,50.37,50.41,50.39,50.39,50.39,50.41,50.45,50.4,50.41,50.47,50.39,50.39,50.38,50.47,50.38,50.47,50.43,50.46,50.39,50.39,50.4,50.47,50.45,50.4,50.46,50.45,50.46,50.41,50.39,50.45,50.43,50.38,50.46,50.43,50.39,50.36,50.4,50.41,50.36,50.38,50.35,50.44,50.38,50.38,50.49,50.42,50.41,50.4,50.41,50.41,50.41,50.37,50.37,50.38,50.4,50.38,50.44,50.46,50.41,50.42,50.37,50.35,50.44,50.38,50.41,50.44,50.4,50.36,50.37,50.4,50.32,50.39,50.37,50.42,50.38,50.37,50.4,50.38,50.43,50.4,50.39,50.36,50.36,50.36,50.39,50.37,50.4,50.37,50.37,50.41,50.36,50.38,50.42,50.4,50.4,50.38,50.36,50.33,50.36,50.36,50.4,50.38,50.34,50.35,50.38,50.36,50.37,50.37,50.38,50.37,50.38,50.38,50.36,50.41,50.36,50.38,50.38,50.46,50.41,50.38,50.42,50.44,50.39,50.38,50.39,50.39,50.42,50.42,50.4,50.4,50.39,50.36,50.33,50.36,50.4,50.38,50.42,50.39,50.36,50.33,50.41,50.41,50.37,50.41,50.4,50.4,50.37,50.38,50.41,50.38,50.37,50.36,50.42,50.39,50.42,50.42,50.42,50.37,50.4,50.39,50.35,50.38,50.45,50.43,50.37,50.36,50.38,50.4,50.4,50.41,50.38,50.38,50.39,50.38,50.36,50.38,50.39,50.39,50.37,50.38,50.42,50.39,50.37,50.42,50.39,50.37,50.41,50.38,50.36,50.38,50.41,50.38,50.36,50.37,50.36,50.38,50.39,50.42,50.43,50.39,50.38,50.35,50.37,50.38,50.4,50.43,50.39,50.35,50.38,50.39,50.4,50.4,50.38,50.37,50.37,50.42,50.4,50.4,50.39,50.43,50.42,50.42,50.38,50.41,50.39,50.4,50.41,50.4,50.4,50.39,50.44,50.41,50.43,50.39,50.37,50.34,50.31,50.39,50.37,50.37,50.39,50.38,50.42,50.38,50.4,50.37,50.4,50.45,50.4,50.4,50.39,50.35,50.4,50.45,50.4,50.4,50.37,50.41,50.45,50.38,50.42,50.46,50.4,50.45,50.4,50.36,50.43,50.46,50.41,50.38,50.47,50.46,50.44,50.41,50.4,50.39,50.39,50.38,50.4,50.41,50.41,50.41,50.37,50.42,50.39,50.39,50.37,50.43,50.46,50.38,50.4,50.38,50.38,50.4,50.45,50.43,50.42,50.45,50.46,50.41,50.5,50.39,50.37,50.3,50.35,50.38,50.41,50.43,50.35]},{"y":2024,"min":[50.31,50.23,50.24,50.25,50.26,50.23,50.23,50.25,50.28,50.26,50.28,50.28,50.34,50.34,50.33,50.32,50.28,50.31,50.3,50.26,50.25,50.29,50.25,50.28,50.28,50.28,50.3,50.29,50.3,50.31,50.31,50.28,50.32,50.31,50.29,50.36,50.38,50.26,50.23,50.21,50.24,50.26,50.29,50.27,50.31,50.26,50.35,50.29,50.28,50.37,50.32,50.31,50.26,50.29,50.27,50.33,50.3,50.31,50.3,50.31,50.3,50.29,50.32,50.36,50.28,50.31,50.26,50.23,50.27,50.24,50.27,50.3,null,50.27,50.28,50.32,50.29,50.25,50.26,50.25,50.29,50.29,50.3,50.3,50.26,50.24,50.3,50.25,50.23,50.28,50.27,50.29,50.26,50.28,50.27,50.26,50.27,50.31,50.3,50.28,50.29,50.28,50.3,50.3,50.33,50.29,50.3,50.29,50.27,50.27,50.24,50.23,50.3,50.31,50.29,50.27,50.28,50.25,50.27,50.29,50.3,50.24,50.23,50.29,50.23,50.28,50.28,50.27,50.27,50.27,50.26,50.26,50.23,50.27,50.24,50.22,50.2,50.22,50.28,50.28,50.3,50.24,50.27,50.29,50.28,50.29,50.26,50.3,50.26,50.25,50.25,50.31,50.26,50.29,50.31,50.27,50.27,50.27,50.29,50.28,50.27,50.26,50.31,50.29,50.26,50.27,50.25,50.3,50.3,50.28,50.28,50.23,50.29,50.32,50.3,50.29,50.25,50.25,50.24,50.27,50.22,50.27,50.3,50.26,50.25,50.25,50.27,50.25,50.32,50.3,50.27,50.28,50.31,50.28,50.3,50.27,50.25,50.27,50.29,50.26,50.25,50.28,50.29,50.28,50.26,50.31,50.28,50.27,50.28,50.26,50.27,50.27,50.3,50.28,50.28,50.29,50.3,50.28,50.28,50.28,50.25,50.27,50.31,50.32,50.28,50.27,50.28,50.31,50.29,50.26,50.28,50.31,50.29,50.31,50.26,50.28,50.23,50.3,50.31,50.28,50.22,50.26,50.29,50.25,50.24,50.25,50.27,50.28,50.23,50.21,50.26,50.26,50.31,50.32,50.29,50.29,50.28,50.28,50.3,50.32,50.27,50.22,50.23,50.27,50.24,50.29,50.29,50.3,50.26,50.26,50.33,50.3,50.27,50.23,50.28,50.31,50.32,50.32,50.3,50.27,50.28,50.29,50.26,50.28,50.28,50.25,50.26,50.28,50.26,50.2,50.27,50.27,50.3,50.3,50.32,50.31,50.27,50.25,50.28,50.23,50.28,50.3,50.29,50.28,50.28,50.31,50.27,50.31,50.3,50.26,50.29,50.25,50.22,50.24,50.29,50.32,50.27,50.3,50.32,50.3,50.3,50.33,50.3,50.25,50.31,50.31,50.35,50.27,50.28,50.31,50.31,50.25,50.29,50.25,50.26,50.28,50.29,50.29,50.3,50.25,50.31,50.26,50.29,50.32,50.26,50.29,50.27,50.28,50.32,50.3,50.34,50.32,50.28,50.31,50.31,50.29,50.31,50.34,50.29,50.33,50.31,50.28,50.3,50.33,50.34,50.31],"max":[50.37,50.36,50.39,50.39,50.35,50.37,50.39,50.39,50.38,50.38,50.41,50.4,50.45,50.44,50.49,50.43,50.38,50.42,50.43,50.39,50.4,50.45,50.46,50.53,50.43,50.44,50.41,50.39,50.41,50.41,50.41,50.45,50.48,50.46,50.47,50.49,50.48,50.47,50.37,50.34,50.38,50.37,50.39,50.41,50.34,50.3,50.37,50.32,50.36,50.38,50.38,50.34,50.29,50.32,50.33,50.38,50.37,50.35,50.33,50.35,50.35,50.35,50.38,50.42,50.34,50.36,50.35,50.27,50.31,50.28,50.4,50.4,null,50.39,50.4,50.43,50.42,50.39,50.42,50.37,50.41,50.42,50.41,50.46,50.42,50.34,50.38,50.37,50.38,50.4,50.39,50.42,50.45,50.37,50.41,50.4,50.37,50.44,50.42,50.43,50.42,50.41,50.43,50.42,50.45,50.41,50.4,50.4,50.39,50.4,50.37,50.33,50.41,50.39,50.44,50.4,50.38,50.36,50.36,50.4,50.39,50.38,50.38,50.4,50.35,50.42,50.38,50.39,50.4,50.36,50.38,50.41,50.35,50.4,50.38,50.35,50.34,50.36,50.37,50.38,50.41,50.39,50.39,50.39,50.37,50.39,50.4,50.41,50.42,50.38,50.35,50.43,50.41,50.4,50.39,50.36,50.38,50.37,50.39,50.38,50.41,50.4,50.42,50.42,50.37,50.37,50.38,50.4,50.4,50.4,50.36,50.35,50.37,50.42,50.38,50.39,50.36,50.37,50.35,50.42,50.34,50.42,50.4,50.4,50.39,50.39,50.37,50.41,50.41,50.38,50.37,50.42,50.42,50.42,50.39,50.38,50.36,50.39,50.39,50.35,50.36,50.39,50.42,50.44,50.38,50.42,50.39,50.39,50.38,50.41,50.38,50.38,50.4,50.39,50.39,50.41,50.42,50.38,50.38,50.4,50.37,50.4,50.39,50.39,50.4,50.39,50.42,50.42,50.4,50.37,50.38,50.4,50.38,50.45,50.37,50.41,50.38,50.41,50.45,50.38,50.34,50.39,50.4,50.32,50.3,50.34,50.36,50.39,50.39,50.34,50.35,50.42,50.43,50.42,50.4,50.38,50.4,50.38,50.4,50.39,50.39,50.36,50.35,50.39,50.38,50.39,50.38,50.39,50.4,50.39,50.45,50.44,50.38,50.35,50.42,50.39,50.42,50.4,50.38,50.37,50.39,50.4,50.36,50.44,50.4,50.36,50.5,50.37,50.37,50.36,50.37,50.39,50.38,50.4,50.44,50.44,50.37,50.37,50.38,50.35,50.39,50.42,50.42,50.41,50.38,50.4,50.39,50.43,50.43,50.36,50.37,50.36,50.37,50.38,50.43,50.41,50.39,50.4,50.43,50.4,50.42,50.44,50.44,50.39,50.43,50.42,50.46,50.42,50.42,50.41,50.42,50.4,50.54,50.35,50.37,50.37,50.43,50.42,50.39,50.35,50.43,50.36,50.41,50.43,50.38,50.38,50.39,50.39,50.43,50.47,50.49,50.43,50.46,50.43,50.43,50.39,50.43,50.47,50.4,50.38,50.38,50.35,50.39,50.42,50.45,50.41]},{"y":2025,"min":[50.38,50.33,50.33,50.25,50.22,50.29,50.3,50.3,50.3,50.32,50.3,50.3,50.3,50.3,50.28,50.3,50.3,50.26,50.28,50.28,50.28,50.23,50.25,50.28,50.26,50.21,50.26,50.26,50.26,50.26,50.25,50.28,50.29,50.3,50.28,50.26,50.27,50.21,50.23,50.24,50.21,50.22,50.25,50.29,50.27,50.26,50.28,50.28,50.26,50.26,50.24,50.3,50.27,50.3,50.29,50.28,50.29,50.29,50.3,50.3,50.32,50.3,50.29,50.27,50.29,50.29,50.25,50.31,50.32,50.3,50.31,50.29,50.3,50.28,50.27,50.29,50.28,50.29,50.28,50.25,50.18,50.25,50.31,50.32,50.31,50.27,50.27,50.3,50.28,50.29,50.28,50.2,50.23,50.24,50.28,50.28,50.31,50.29,50.3,50.31,50.33,50.27,50.3,50.31,50.22,50.29,50.32,50.31,50.28,50.31,50.32,50.3,50.26,50.27,50.3,50.26,50.27,50.29,50.27,50.26,50.27,50.29,50.28,50.33,50.28,50.3,50.2,50.24,50.26,50.26,50.24,50.22,50.22,50.26,50.25,50.27,50.28,50.31,50.29,50.29,50.3,50.3,50.29,50.25,50.24,50.28,50.28,50.3,50.29,50.29,50.25,50.28,50.29,50.28,50.28,50.26,50.26,50.27,50.31,50.27,50.26,50.27,50.18,50.2,50.2,50.3,50.27,50.26,50.27,50.25,50.25,50.25,50.27,50.3,50.28,50.28,50.26,50.28,50.27,50.3,50.27,50.26,50.28,50.24,50.26,50.26,50.26,50.3,50.3,50.29,50.28,50.26,50.27,50.29,50.3,50.27,50.27,50.31,50.29,50.22,50.27,50.29,50.31,50.3,50.27,50.28,50.26,50.25,50.29,50.3,50.27,50.3,50.29,50.29,50.29,50.3,50.31,50.29,50.26,50.28,50.26,50.28,50.26,50.21,50.24,50.25,50.28,50.27,50.29,50.29,50.31,50.26,50.28,50.29,50.28,50.27,50.3,50.25,50.26,50.28,50.26,50.31,50.27,50.29,50.29,50.25,50.28,50.3,50.29,50.25,50.26,50.26,50.26,50.26,50.28,50.26,50.31,50.28,50.31,50.29,50.27,50.23,50.26,50.29,50.28,50.28,50.16,50.19,50.24,50.27,50.27,50.27,50.25,50.22,50.25,50.26,50.27,50.33,50.31,50.27,50.27,50.28,50.3,50.24,50.28,50.23,50.27,50.24,50.24,50.24,50.18,50.21,50.24,50.24,50.27,50.24,50.32,50.29,50.33,50.32,50.3,50.24,50.25,50.23,50.26,50.3,50.31,50.26,50.24,50.2,50.24,50.25,50.28,50.25,50.27,50.24,50.24,50.25,50.21,50.29,50.31,50.27,50.23,50.26,50.25,50.25,50.25,50.28,50.28,50.28,50.25,50.25,50.24,50.26,50.28,50.27,50.27,50.26,50.26,50.24,50.3,50.28,50.24,50.27,50.28,50.25,50.27,50.28,50.28,50.26,50.25,50.23,50.25,50.25,50.25,50.2,50.2,50.23,50.24,50.28,50.31,50.31,50.31,50.29,50.32],"max":[50.47,50.43,50.48,50.36,50.37,50.43,50.41,50.48,50.4,50.44,50.41,50.43,50.42,50.47,50.41,50.39,50.39,50.37,50.41,50.48,50.38,50.36,50.4,50.38,50.37,50.35,50.36,50.38,50.41,50.38,50.38,50.4,50.4,50.39,50.41,50.42,50.4,50.34,50.36,50.37,50.36,50.33,50.37,50.41,50.39,50.39,50.38,50.39,50.41,50.38,50.39,50.41,50.38,50.44,50.42,50.45,50.39,50.41,50.43,50.42,50.41,50.4,50.42,50.39,50.38,50.39,50.37,50.41,50.4,50.41,50.41,50.38,50.41,50.42,50.39,50.4,50.41,50.38,50.38,50.39,50.33,50.41,50.43,50.43,50.42,50.37,50.36,50.41,50.48,50.46,50.4,50.41,50.35,50.38,50.37,50.4,50.4,50.42,50.41,50.41,50.47,50.38,50.42,50.39,50.36,50.45,50.43,50.43,50.36,50.41,50.43,50.44,50.37,50.38,50.41,50.4,50.4,50.41,50.39,50.38,50.37,50.42,50.39,50.42,50.43,50.41,50.36,50.4,50.38,50.39,50.38,50.39,50.36,50.42,50.35,50.41,50.4,50.41,50.41,50.4,50.38,50.39,50.44,50.35,50.41,50.41,50.39,50.4,50.41,50.41,50.33,50.41,50.41,50.4,50.42,50.38,50.38,50.36,50.43,50.4,50.4,50.41,50.34,50.31,50.35,50.43,50.37,50.35,50.37,50.38,50.35,50.37,50.35,50.42,50.41,50.41,50.4,50.41,50.41,50.43,50.36,50.38,50.38,50.41,50.34,50.38,50.38,50.43,50.39,50.4,50.38,50.39,50.4,50.39,50.44,50.43,50.38,50.43,50.45,50.33,50.42,50.39,50.45,50.42,50.4,50.37,50.33,50.37,50.41,50.41,50.38,50.41,50.43,50.39,50.42,50.43,50.43,50.39,50.38,50.4,50.37,50.38,50.36,50.38,50.33,50.35,50.42,50.39,50.43,50.42,50.39,50.44,50.4,50.4,50.37,50.37,50.38,50.37,50.44,50.4,50.4,50.41,50.37,50.38,50.39,50.36,50.41,50.42,50.4,50.38,50.38,50.42,50.41,50.37,50.41,50.4,50.42,50.51,50.45,50.39,50.37,50.35,50.38,50.42,50.4,50.42,50.35,50.35,50.36,50.38,50.39,50.37,50.37,50.39,50.36,50.35,50.4,50.46,50.41,50.38,50.38,50.41,50.41,50.37,50.36,50.35,50.4,50.38,50.36,50.36,50.31,50.33,50.34,50.38,50.37,50.35,50.5,50.38,50.53,50.47,50.41,50.4,50.43,50.34,50.38,50.4,50.41,50.4,50.38,50.34,50.35,50.36,50.39,50.4,50.44,50.34,50.36,50.38,50.36,50.45,50.46,50.41,50.35,50.43,50.37,50.37,50.36,50.41,50.4,50.4,50.39,50.4,50.41,50.39,50.41,50.41,50.38,50.36,50.37,50.37,50.41,50.43,50.38,50.41,50.43,50.39,50.34,50.38,50.41,50.39,50.41,50.38,50.37,50.35,50.33,50.34,50.32,50.37,50.27,50.33,50.41,50.44,50.45,50.38,50.32]}]